LICENSE
MANIFEST.in
README.md
pyproject.toml
setup.py
lightbinpack/__init__.py
lightbinpack/packing.py
lightbinpack.egg-info/PKG-INFO
lightbinpack.egg-info/SOURCES.txt
lightbinpack.egg-info/dependency_links.txt
lightbinpack.egg-info/not-zip-safe
lightbinpack.egg-info/requires.txt
lightbinpack.egg-info/top_level.txt
lightbinpack/cpp/__init__.py
lightbinpack/cpp/bfd.cpp
lightbinpack/cpp/ffd.cpp
lightbinpack/cpp/load_balance.cpp
lightbinpack/cpp/nf.cpp
lightbinpack/cpp/obfd.cpp
lightbinpack/cpp/obfdp.cpp
lightbinpack/cpp/ogbfd.cpp
lightbinpack/cpp/ogbfdp.cpp
lightbinpack/cpp/ohgbfd.cpp
lightbinpack/cpp/oshgbfd.cpp
lightbinpack/cpp/radix_merge.cpp
lightbinpack/cpp/radix_sort.cpp