Metadata-Version: 2.4
Name: lightbinpack
Version: 0.1.1
Summary: A lightweight library for solving bin packing problems
Home-page: https://github.com/TechxGenus/LightBinPack
Author: TechxGenus
Requires-Python: >=3.6
License-File: LICENSE
Requires-Dist: pybind11>=2.6.0
Requires-Dist: numpy>=1.19.0
Dynamic: author
Dynamic: home-page
Dynamic: license-file
Dynamic: requires-dist
Dynamic: requires-python
Dynamic: summary
